googoodan/__init__.py
googoodan/game.py
googoodan-0.1.1.dist-info/LICENSE
googoodan-0.1.1.dist-info/METADATA
googoodan-0.1.1.dist-info/WHEEL
googoodan-0.1.1.dist-info/entry_points.txt
googoodan-0.1.1.dist-info/top_level.txt
googoodan-0.1.1.dist-info/RECORD
