Metadata-Version: 2.2
Name: googoodan
Version: 0.1.1
Summary: CLI 구구단 게임
Author-email: Euiyun Kim <geniuskey@gmail.com>
License: MIT
Project-URL: Homepage, https://github.com/geniuskey/googoodan
Project-URL: Repository, https://github.com/geniuskey/googoodan
Keywords: multiplication,game,CLI,python
Classifier: Development Status :: 4 - Beta
Classifier: Intended Audience :: Education
Classifier: License :: OSI Approved :: MIT License
Classifier: Programming Language :: Python :: 3
Classifier: Programming Language :: Python :: 3.8
Classifier: Programming Language :: Python :: 3.9
Classifier: Programming Language :: Python :: 3.10
Classifier: Programming Language :: Python :: 3.11
Classifier: Operating System :: OS Independent
License-File: LICENSE
Requires-Dist: terminaltexteffects
